setup.cfg
setup.py
pyhorizon/__init__.py
pyhorizon/pyhorizon.py
pyhorizon.egg-info/PKG-INFO
pyhorizon.egg-info/SOURCES.txt
pyhorizon.egg-info/dependency_links.txt
pyhorizon.egg-info/requires.txt
pyhorizon.egg-info/top_level.txt