Metadata-Version: 1.1
Name: pyhorizon
Version: 0.2
Summary: Pyhorizon is a thin wrapper on top of the NASA API.
Home-page: https://github.com/EricDalrymple91/pyhorizon
Author: Eric Dalrymple
Author-email: ericjdalrymple@gmail.com
License: MIT
Download-URL: https://github.com/EricDalrymple91/pyhorizon/tarball/0.1
Platform: UNKNOWN
Classifier: License :: OSI Approved :: MIT License
Classifier: Topic :: Software Development :: Libraries :: Python Modules
Classifier: Topic :: Text Processing
Classifier: Topic :: Scientific/Engineering :: Astronomy
Classifier: Topic :: Scientific/Engineering :: Physics
Classifier: Topic :: Scientific/Engineering :: Visualization
